[
  {
    "title": "Senior Materials Engineer ",
    "company": "Freeform",
    "location": "Los Angeles, CA",
    "applicationURL": "https://z4g07sa50j.execute-api.us-east-1.amazonaws.com/production/track?id=xb0v2lx2bh",
    "imageURL": "https://images.squarespace-cdn.com/content/v1/61fb0a0cf413a1740c80e064/3c18ce36-87a3-49ff-a703-17839b58ae8e/freeform_logo.png?format=1000w"

  },
  {
    "title": "Senior Mechanical Engineer",
    "company": "Freeform",
    "location": "Los Angeles, CA",
    "applicationURL": "https://z4g07sa50j.execute-api.us-east-1.amazonaws.com/production/track?id=zj99ue6ege",
    "imageURL": "https://images.squarespace-cdn.com/content/v1/61fb0a0cf413a1740c80e064/3c18ce36-87a3-49ff-a703-17839b58ae8e/freeform_logo.png?format=1000w"
  },
  {
    "title": "Manufacturing Operations Engineer",
    "company": "Freeform",
    "location": "Los Angeles, CA",
    "applicationURL": "https://z4g07sa50j.execute-api.us-east-1.amazonaws.com/production/track?id=6t7temh1f7",
    "imageURL": "https://images.squarespace-cdn.com/content/v1/61fb0a0cf413a1740c80e064/3c18ce36-87a3-49ff-a703-17839b58ae8e/freeform_logo.png?format=1000w"

  },
  {
    "title": "Senior Controls Engineer",
    "company": "DURIN",
    "location": "El Segundo, CA",
    "applicationURL": "https://z4g07sa50j.execute-api.us-east-1.amazonaws.com/production/track?id=xlt8lt9fnn",
    "imageURL": "https://media.licdn.com/dms/image/v2/D4E0BAQH79pJo6C9D6Q/company-logo_100_100/company-logo_100_100/0/1732564438373/durinmining_logo?e=1746662400&v=beta&t=nqR0G0Cu0-r2IDI1A2i9p7_ogsLCu532iimphbeGa4c"

  },
  {
    "title": "Senior Software Engineer",
    "company": "DURIN",
    "location": "El Segundo, CA",
    "applicationURL": "https://z4g07sa50j.execute-api.us-east-1.amazonaws.com/production/track?id=wet0h1o7lw",
    "imageURL": "https://media.licdn.com/dms/image/v2/D4E0BAQH79pJo6C9D6Q/company-logo_100_100/company-logo_100_100/0/1732564438373/durinmining_logo?e=1746662400&v=beta&t=nqR0G0Cu0-r2IDI1A2i9p7_ogsLCu532iimphbeGa4c"
  }
]
